{
  "slug": "malphite",
  "name": {
    "ru_ru": "МАЛЬФИТ",
    "pt_br": "MALPHITE",
    "en_us": "MALPHITE",
    "it_it": "MALPHITE",
    "tr_tr": "MALPHITE",
    "de_de": "MALPHITE",
    "ms_my": "MALPHITE",
    "vi_vn": "MALPHITE",
    "ko_kr": "말파이트",
    "ja_jp": "マルファイト",
    "es_es": "MALPHITE",
    "fr_fr": "MALPHITE",
    "th_th": "MALPHITE",
    "zh_tw": "墨菲特",
    "en_gb": "MALPHITE",
    "pl_pl": "MALPHITE",
    "es_mx": "MALPHITE",
    "en_sg": "MALPHITE",
    "ar_ae": "مالفايت"
  },
  "roles": [
    "tank"
  ],
  "difficulty": "low"
}