{
  "slug": "twisted-fate",
  "name": {
    "ru_ru": "ТВИСТЕД ФЭЙТ",
    "pt_br": "TWISTED FATE",
    "en_us": "TWISTED FATE",
    "it_it": "TWISTED FATE",
    "tr_tr": "TWISTED FATE",
    "de_de": "TWISTED FATE",
    "ms_my": "TWISTED FATE",
    "vi_vn": "TWISTED FATE",
    "ko_kr": "트위스티드 페이트",
    "ja_jp": "ツイステッド・フェイト",
    "es_es": "TWISTED FATE",
    "fr_fr": "TWISTED FATE",
    "th_th": "TWISTED FATE",
    "zh_tw": "逆命",
    "en_gb": "TWISTED FATE",
    "pl_pl": "TWISTED FATE",
    "es_mx": "TWISTED FATE",
    "en_sg": "TWISTED FATE",
    "ar_ae": "تويستد فايت"
  },
  "roles": [
    "mage",
    "marksman"
  ],
  "difficulty": "medium"
}