{
  "slug": "akshan",
  "name": "АКШАН",
  "cnHeroId": "10100",
  "history": [
    {
      "date": "2025-11-24",
      "cnStats": {
        "overall": {
          "mid": {
            "rank": 1,
            "winRate": 48.55,
            "pickRate": 1.02,
            "banRate": 0.06,
            "strengthLevel": 5
          }
        },
        "king": {
          "mid": {
            "rank": 1,
            "winRate": 47.11,
            "pickRate": 1.13,
            "banRate": 0.02,
            "strengthLevel": 5
          }
        },
        "peak": {
          "mid": {
            "rank": 1,
            "winRate": 45.7,
            "pickRate": 1.06,
            "banRate": 0.06,
            "strengthLevel": 5
          }
        }
      }
    },
    {
      "date": "2025-11-25",
      "cnStats": {
        "king": {
          "mid": {
            "rank": 1,
            "winRate": 50.76,
            "pickRate": 1.09,
            "banRate": 0.02,
            "strengthLevel": 5
          }
        }
      }
    },
    {
      "date": "2025-11-27",
      "cnStats": {
        "king": {
          "mid": {
            "rank": 1,
            "winRate": 48.35,
            "pickRate": 1.03,
            "banRate": 0.04,
            "strengthLevel": 5
          }
        }
      }
    },
    {
      "date": "2025-11-28",
      "cnStats": {
        "king": {
          "mid": {
            "rank": 1,
            "winRate": 52.39,
            "pickRate": 1.02,
            "banRate": 0.03,
            "strengthLevel": 5
          }
        }
      }
    },
    {
      "date": "2025-11-29",
      "cnStats": {
        "king": {
          "mid": {
            "rank": 1,
            "winRate": 48.13,
            "pickRate": 1.19,
            "banRate": 0.04,
            "strengthLevel": 5
          }
        }
      }
    },
    {
      "date": "2025-11-30",
      "cnStats": {
        "overall": {
          "mid": {
            "rank": 1,
            "winRate": 50.23,
            "pickRate": 1,
            "banRate": 0.06,
            "strengthLevel": 5
          }
        },
        "king": {
          "mid": {
            "rank": 1,
            "winRate": 45.31,
            "pickRate": 1.16,
            "banRate": 0.05,
            "strengthLevel": 5
          }
        },
        "peak": {
          "mid": {
            "rank": 1,
            "winRate": 47.57,
            "pickRate": 1.12,
            "banRate": 0.07,
            "strengthLevel": 5
          }
        }
      }
    }
  ]
}