{
  "slug": "blitzcrank",
  "name": "БЛИЦКРАНК",
  "cnHeroId": "10033",
  "history": [
    {
      "date": "2025-11-24",
      "cnStats": {
        "overall": {
          "support": {
            "rank": 4,
            "winRate": 49.74,
            "pickRate": 9.59,
            "banRate": 3.79,
            "strengthLevel": 3
          }
        },
        "diamondPlus": {
          "support": {
            "rank": 4,
            "winRate": 50.02,
            "pickRate": 7.59,
            "banRate": 2.85,
            "strengthLevel": 3
          }
        },
        "masterPlus": {
          "support": {
            "rank": 4,
            "winRate": 50.46,
            "pickRate": 7.48,
            "banRate": 2.9,
            "strengthLevel": 3
          }
        },
        "king": {
          "support": {
            "rank": 4,
            "winRate": 52.04,
            "pickRate": 7.18,
            "banRate": 1.36,
            "strengthLevel": 3
          }
        },
        "peak": {
          "support": {
            "rank": 4,
            "winRate": 51.96,
            "pickRate": 6.91,
            "banRate": 1.57,
            "strengthLevel": 3
          }
        }
      }
    },
    {
      "date": "2025-11-25",
      "cnStats": {
        "overall": {
          "support": {
            "rank": 4,
            "winRate": 50.09,
            "pickRate": 9.85,
            "banRate": 3.8,
            "strengthLevel": 3
          }
        },
        "diamondPlus": {
          "support": {
            "rank": 4,
            "winRate": 49.99,
            "pickRate": 7.71,
            "banRate": 2.84,
            "strengthLevel": 3
          }
        },
        "masterPlus": {
          "support": {
            "rank": 4,
            "winRate": 49.92,
            "pickRate": 7.54,
            "banRate": 2.84,
            "strengthLevel": 3
          }
        },
        "king": {
          "support": {
            "rank": 4,
            "winRate": 50.94,
            "pickRate": 7.49,
            "banRate": 1.31,
            "strengthLevel": 3
          }
        },
        "peak": {
          "support": {
            "rank": 4,
            "winRate": 50.93,
            "pickRate": 6.52,
            "banRate": 1.55,
            "strengthLevel": 4
          }
        }
      }
    },
    {
      "date": "2025-11-26",
      "cnStats": {
        "overall": {
          "support": {
            "rank": 4,
            "winRate": 50.65,
            "pickRate": 9.77,
            "banRate": 3.79,
            "strengthLevel": 3
          }
        },
        "diamondPlus": {
          "support": {
            "rank": 4,
            "winRate": 49.83,
            "pickRate": 7.76,
            "banRate": 2.87,
            "strengthLevel": 3
          }
        },
        "masterPlus": {
          "support": {
            "rank": 4,
            "winRate": 50.01,
            "pickRate": 7.63,
            "banRate": 2.89,
            "strengthLevel": 3
          }
        },
        "king": {
          "support": {
            "rank": 4,
            "winRate": 51.61,
            "pickRate": 7.39,
            "banRate": 1.28,
            "strengthLevel": 3
          }
        },
        "peak": {
          "support": {
            "rank": 4,
            "winRate": 50.47,
            "pickRate": 6.52,
            "banRate": 1.58,
            "strengthLevel": 4
          }
        }
      }
    },
    {
      "date": "2025-11-27",
      "cnStats": {
        "overall": {
          "support": {
            "rank": 4,
            "winRate": 50.28,
            "pickRate": 9.01,
            "banRate": 3.84,
            "strengthLevel": 3
          }
        },
        "diamondPlus": {
          "support": {
            "rank": 4,
            "winRate": 50.17,
            "pickRate": 7.65,
            "banRate": 2.85,
            "strengthLevel": 3
          }
        },
        "masterPlus": {
          "support": {
            "rank": 4,
            "winRate": 50.24,
            "pickRate": 7.58,
            "banRate": 2.87,
            "strengthLevel": 3
          }
        },
        "king": {
          "support": {
            "rank": 4,
            "winRate": 51.11,
            "pickRate": 6.98,
            "banRate": 1.21,
            "strengthLevel": 3
          }
        },
        "peak": {
          "support": {
            "rank": 4,
            "winRate": 51.17,
            "pickRate": 6.84,
            "banRate": 1.68,
            "strengthLevel": 3
          }
        }
      }
    },
    {
      "date": "2025-11-28",
      "cnStats": {
        "overall": {
          "support": {
            "rank": 4,
            "winRate": 49.72,
            "pickRate": 9.12,
            "banRate": 3.9,
            "strengthLevel": 3
          }
        },
        "diamondPlus": {
          "support": {
            "rank": 4,
            "winRate": 50.36,
            "pickRate": 7.66,
            "banRate": 2.93,
            "strengthLevel": 3
          }
        },
        "masterPlus": {
          "support": {
            "rank": 4,
            "winRate": 50.53,
            "pickRate": 7.59,
            "banRate": 2.96,
            "strengthLevel": 3
          }
        },
        "king": {
          "support": {
            "rank": 4,
            "winRate": 51.3,
            "pickRate": 7.31,
            "banRate": 1.38,
            "strengthLevel": 3
          }
        },
        "peak": {
          "support": {
            "rank": 4,
            "winRate": 51.22,
            "pickRate": 6.73,
            "banRate": 1.46,
            "strengthLevel": 4
          }
        }
      }
    },
    {
      "date": "2025-11-29",
      "cnStats": {
        "overall": {
          "support": {
            "rank": 4,
            "winRate": 50.92,
            "pickRate": 9.12,
            "banRate": 3.87,
            "strengthLevel": 3
          }
        },
        "diamondPlus": {
          "support": {
            "rank": 4,
            "winRate": 50.3,
            "pickRate": 7.68,
            "banRate": 2.92,
            "strengthLevel": 3
          }
        },
        "masterPlus": {
          "support": {
            "rank": 4,
            "winRate": 50.45,
            "pickRate": 7.64,
            "banRate": 2.97,
            "strengthLevel": 3
          }
        },
        "king": {
          "support": {
            "rank": 4,
            "winRate": 52.09,
            "pickRate": 6.84,
            "banRate": 1.56,
            "strengthLevel": 3
          }
        },
        "peak": {
          "support": {
            "rank": 4,
            "winRate": 52.36,
            "pickRate": 6.71,
            "banRate": 1.65,
            "strengthLevel": 4
          }
        }
      }
    },
    {
      "date": "2025-11-30",
      "cnStats": {
        "overall": {
          "support": {
            "rank": 4,
            "winRate": 50.51,
            "pickRate": 8.91,
            "banRate": 3.92,
            "strengthLevel": 3
          }
        },
        "diamondPlus": {
          "support": {
            "rank": 4,
            "winRate": 50.12,
            "pickRate": 7.7,
            "banRate": 3.15,
            "strengthLevel": 3
          }
        },
        "masterPlus": {
          "support": {
            "rank": 4,
            "winRate": 50.19,
            "pickRate": 7.69,
            "banRate": 3.19,
            "strengthLevel": 3
          }
        },
        "king": {
          "support": {
            "rank": 4,
            "winRate": 52.22,
            "pickRate": 7.28,
            "banRate": 1.69,
            "strengthLevel": 3
          }
        },
        "peak": {
          "support": {
            "rank": 4,
            "winRate": 51.05,
            "pickRate": 7.09,
            "banRate": 1.54,
            "strengthLevel": 4
          }
        }
      }
    },
    {
      "date": "2025-12-01",
      "cnStats": {
        "overall": {
          "support": {
            "rank": 4,
            "winRate": 50.87,
            "pickRate": 9.17,
            "banRate": 3.85,
            "strengthLevel": 3
          }
        },
        "diamondPlus": {
          "support": {
            "rank": 4,
            "winRate": 50.14,
            "pickRate": 7.79,
            "banRate": 3.17,
            "strengthLevel": 3
          }
        },
        "masterPlus": {
          "support": {
            "rank": 4,
            "winRate": 50.15,
            "pickRate": 7.75,
            "banRate": 3.22,
            "strengthLevel": 3
          }
        },
        "king": {
          "support": {
            "rank": 4,
            "winRate": 50.31,
            "pickRate": 7.33,
            "banRate": 1.68,
            "strengthLevel": 3
          }
        },
        "peak": {
          "support": {
            "rank": 4,
            "winRate": 51.27,
            "pickRate": 7.07,
            "banRate": 1.7,
            "strengthLevel": 4
          }
        }
      }
    },
    {
      "date": "2025-12-02",
      "cnStats": {
        "overall": {
          "support": {
            "rank": 4,
            "winRate": 50.72,
            "pickRate": 9.44,
            "banRate": 3.82,
            "strengthLevel": 3
          }
        },
        "diamondPlus": {
          "support": {
            "rank": 4,
            "winRate": 49.91,
            "pickRate": 7.88,
            "banRate": 3.09,
            "strengthLevel": 3
          }
        },
        "masterPlus": {
          "support": {
            "rank": 4,
            "winRate": 50.03,
            "pickRate": 7.83,
            "banRate": 3.11,
            "strengthLevel": 3
          }
        },
        "king": {
          "support": {
            "rank": 4,
            "winRate": 50.56,
            "pickRate": 7.22,
            "banRate": 1.63,
            "strengthLevel": 3
          }
        },
        "peak": {
          "support": {
            "rank": 4,
            "winRate": 51.43,
            "pickRate": 7.01,
            "banRate": 1.86,
            "strengthLevel": 4
          }
        }
      }
    },
    {
      "date": "2025-12-03",
      "cnStats": {
        "overall": {
          "support": {
            "rank": 4,
            "winRate": 50.01,
            "pickRate": 9.52,
            "banRate": 3.98,
            "strengthLevel": 3
          }
        },
        "diamondPlus": {
          "support": {
            "rank": 4,
            "winRate": 50.06,
            "pickRate": 7.9,
            "banRate": 3.09,
            "strengthLevel": 3
          }
        },
        "masterPlus": {
          "support": {
            "rank": 4,
            "winRate": 50.18,
            "pickRate": 7.84,
            "banRate": 3.1,
            "strengthLevel": 3
          }
        },
        "king": {
          "support": {
            "rank": 4,
            "winRate": 51.69,
            "pickRate": 7.09,
            "banRate": 1.86,
            "strengthLevel": 3
          }
        },
        "peak": {
          "support": {
            "rank": 4,
            "winRate": 50.43,
            "pickRate": 7.09,
            "banRate": 1.95,
            "strengthLevel": 4
          }
        }
      }
    },
    {
      "date": "2025-12-04",
      "cnStats": {
        "overall": {
          "support": {
            "rank": 4,
            "winRate": 50.86,
            "pickRate": 9.38,
            "banRate": 4.09,
            "strengthLevel": 3
          }
        },
        "diamondPlus": {
          "support": {
            "rank": 4,
            "winRate": 50.06,
            "pickRate": 7.94,
            "banRate": 3.11,
            "strengthLevel": 3
          }
        },
        "masterPlus": {
          "support": {
            "rank": 4,
            "winRate": 50.04,
            "pickRate": 7.89,
            "banRate": 3.13,
            "strengthLevel": 3
          }
        },
        "king": {
          "support": {
            "rank": 4,
            "winRate": 51.45,
            "pickRate": 7.35,
            "banRate": 1.78,
            "strengthLevel": 3
          }
        },
        "peak": {
          "support": {
            "rank": 4,
            "winRate": 50.6,
            "pickRate": 7.35,
            "banRate": 1.86,
            "strengthLevel": 3
          }
        }
      }
    },
    {
      "date": "2025-12-05",
      "cnStats": {
        "overall": {
          "support": {
            "rank": 4,
            "winRate": 50.48,
            "pickRate": 9.68,
            "banRate": 3.89,
            "strengthLevel": 3
          }
        },
        "diamondPlus": {
          "support": {
            "rank": 4,
            "winRate": 50.13,
            "pickRate": 8.02,
            "banRate": 3.15,
            "strengthLevel": 3
          }
        },
        "masterPlus": {
          "support": {
            "rank": 4,
            "winRate": 50.1,
            "pickRate": 7.94,
            "banRate": 3.19,
            "strengthLevel": 3
          }
        },
        "king": {
          "support": {
            "rank": 4,
            "winRate": 50.88,
            "pickRate": 7.42,
            "banRate": 1.95,
            "strengthLevel": 3
          }
        },
        "peak": {
          "support": {
            "rank": 4,
            "winRate": 51.66,
            "pickRate": 7.35,
            "banRate": 1.74,
            "strengthLevel": 3
          }
        }
      }
    },
    {
      "date": "2025-12-06",
      "cnStats": {
        "overall": {
          "support": {
            "rank": 4,
            "winRate": 50.71,
            "pickRate": 9.39,
            "banRate": 3.92,
            "strengthLevel": 3
          }
        },
        "diamondPlus": {
          "support": {
            "rank": 4,
            "winRate": 50.45,
            "pickRate": 7.96,
            "banRate": 3.15,
            "strengthLevel": 3
          }
        },
        "masterPlus": {
          "support": {
            "rank": 4,
            "winRate": 50.37,
            "pickRate": 7.91,
            "banRate": 3.19,
            "strengthLevel": 3
          }
        },
        "king": {
          "support": {
            "rank": 4,
            "winRate": 50.21,
            "pickRate": 7.36,
            "banRate": 1.97,
            "strengthLevel": 3
          }
        },
        "peak": {
          "support": {
            "rank": 4,
            "winRate": 50.88,
            "pickRate": 7.22,
            "banRate": 1.77,
            "strengthLevel": 4
          }
        }
      }
    },
    {
      "date": "2025-12-07",
      "cnStats": {
        "overall": {
          "support": {
            "rank": 4,
            "winRate": 50.57,
            "pickRate": 9.32,
            "banRate": 4,
            "strengthLevel": 3
          }
        },
        "diamondPlus": {
          "support": {
            "rank": 4,
            "winRate": 50.23,
            "pickRate": 7.97,
            "banRate": 3.26,
            "strengthLevel": 3
          }
        },
        "masterPlus": {
          "support": {
            "rank": 4,
            "winRate": 50.25,
            "pickRate": 7.94,
            "banRate": 3.29,
            "strengthLevel": 3
          }
        },
        "king": {
          "support": {
            "rank": 4,
            "winRate": 50.53,
            "pickRate": 7.46,
            "banRate": 2.05,
            "strengthLevel": 3
          }
        },
        "peak": {
          "support": {
            "rank": 4,
            "winRate": 50.8,
            "pickRate": 7.27,
            "banRate": 1.91,
            "strengthLevel": 4
          }
        }
      }
    }
  ]
}