{
  "slug": "seraphine",
  "name": "СЕРАФИНА",
  "cnHeroId": "10034",
  "history": [
    {
      "date": "2025-11-24",
      "cnStats": {
        "overall": {
          "support": {
            "rank": 4,
            "winRate": 49.02,
            "pickRate": 9.59,
            "banRate": 2.27,
            "strengthLevel": 3
          }
        },
        "diamondPlus": {
          "support": {
            "rank": 4,
            "winRate": 49.34,
            "pickRate": 7.86,
            "banRate": 1.26,
            "strengthLevel": 4
          }
        },
        "masterPlus": {
          "support": {
            "rank": 4,
            "winRate": 49.69,
            "pickRate": 7.79,
            "banRate": 1.08,
            "strengthLevel": 4
          }
        },
        "king": {
          "support": {
            "rank": 4,
            "winRate": 48.36,
            "pickRate": 5.78,
            "banRate": 0.22,
            "strengthLevel": 4
          }
        },
        "peak": {
          "support": {
            "rank": 4,
            "winRate": 50.61,
            "pickRate": 7.98,
            "banRate": 0.41,
            "strengthLevel": 3
          }
        }
      }
    },
    {
      "date": "2025-11-25",
      "cnStats": {
        "overall": {
          "mid": {
            "rank": 1,
            "winRate": 47.05,
            "pickRate": 1.01,
            "banRate": 2.2,
            "strengthLevel": 5
          },
          "support": {
            "rank": 4,
            "winRate": 49.27,
            "pickRate": 9.5,
            "banRate": 2.2,
            "strengthLevel": 3
          }
        },
        "diamondPlus": {
          "support": {
            "rank": 4,
            "winRate": 49.66,
            "pickRate": 7.92,
            "banRate": 1.25,
            "strengthLevel": 3
          }
        },
        "masterPlus": {
          "support": {
            "rank": 4,
            "winRate": 49.76,
            "pickRate": 7.83,
            "banRate": 1.07,
            "strengthLevel": 3
          }
        },
        "king": {
          "support": {
            "rank": 4,
            "winRate": 50.83,
            "pickRate": 5.94,
            "banRate": 0.2,
            "strengthLevel": 4
          }
        },
        "peak": {
          "support": {
            "rank": 4,
            "winRate": 51.53,
            "pickRate": 7.76,
            "banRate": 0.49,
            "strengthLevel": 3
          }
        }
      }
    },
    {
      "date": "2025-11-26",
      "cnStats": {
        "overall": {
          "mid": {
            "rank": 1,
            "winRate": 47.8,
            "pickRate": 1,
            "banRate": 2.22,
            "strengthLevel": 5
          },
          "support": {
            "rank": 4,
            "winRate": 48.6,
            "pickRate": 9.37,
            "banRate": 2.22,
            "strengthLevel": 3
          }
        },
        "diamondPlus": {
          "support": {
            "rank": 4,
            "winRate": 49.12,
            "pickRate": 7.86,
            "banRate": 1.28,
            "strengthLevel": 4
          }
        },
        "masterPlus": {
          "support": {
            "rank": 4,
            "winRate": 49.48,
            "pickRate": 7.76,
            "banRate": 1.13,
            "strengthLevel": 4
          }
        },
        "king": {
          "support": {
            "rank": 4,
            "winRate": 49.18,
            "pickRate": 5.65,
            "banRate": 0.15,
            "strengthLevel": 4
          }
        },
        "peak": {
          "support": {
            "rank": 4,
            "winRate": 52.16,
            "pickRate": 7.7,
            "banRate": 0.43,
            "strengthLevel": 3
          }
        }
      }
    },
    {
      "date": "2025-11-27",
      "cnStats": {
        "overall": {
          "mid": {
            "rank": 1,
            "winRate": 47.21,
            "pickRate": 1.09,
            "banRate": 2.3,
            "strengthLevel": 5
          },
          "support": {
            "rank": 4,
            "winRate": 49.11,
            "pickRate": 10,
            "banRate": 2.3,
            "strengthLevel": 3
          }
        },
        "diamondPlus": {
          "support": {
            "rank": 4,
            "winRate": 49.35,
            "pickRate": 7.97,
            "banRate": 1.27,
            "strengthLevel": 3
          }
        },
        "masterPlus": {
          "support": {
            "rank": 4,
            "winRate": 49.53,
            "pickRate": 7.84,
            "banRate": 1.1,
            "strengthLevel": 3
          }
        },
        "king": {
          "support": {
            "rank": 4,
            "winRate": 48.37,
            "pickRate": 5.72,
            "banRate": 0.2,
            "strengthLevel": 4
          }
        },
        "peak": {
          "support": {
            "rank": 4,
            "winRate": 50.13,
            "pickRate": 7.65,
            "banRate": 0.52,
            "strengthLevel": 3
          }
        }
      }
    }
  ]
}